{"api_common.md":"d98a0058","api_filter.md":"43659f05","api_form.md":"b008d903","api_index.md":"aa58592a","api_message.md":"2d95ae96","api_page.md":"869ec2b7","api_request.md":"adc364b1","components_element-plus_batch-table.md":"c73a37bd","components_element-plus_breadcrumb.md":"28bd98b6","components_element-plus_button.md":"e1dd81b8","components_element-plus_date-picker.md":"6fb5af0d","components_element-plus_dialog.md":"2ea7548c","components_element-plus_guide.md":"04de08eb","components_element-plus_index.md":"a61daf36","components_element-plus_input-number.md":"418814b8","components_element-plus_input.md":"aa37e2f4","components_element-plus_layout.md":"4b1de4a7","components_element-plus_pagination.md":"175219d7","components_element-plus_picker.md":"c45687c3","components_element-plus_table.md":"32546353","components_element-plus_tabs.md":"296d264b","components_element-plus_tooltip.md":"2189ede6","components_vant_button.md":"38121ea2","components_vant_index.md":"da93831b","components_vant_layout.md":"27f6aa4c","config_index.md":"47eaab25","directives_autofocus.md":"bfa27634","directives_index.md":"626a16c8","directives_money.md":"269a531a","directives_params.md":"ea3f5399","guide_best-practice.md":"c8a50fc2","guide_components.md":"b431857f","guide_config.md":"ecff9a8c","guide_index.md":"47495035","index.md":"08210525"}
